{"type": "Feature", "id": 12523013, "geometry": {"type": "Point", "coordinates": [31.9347, -13.2597]}, "properties": {"woe:id": 12523013, "woe:parent_id": 1576927, "woe:name": "Mfuwe Airport", "woe:placetype": 14, "woe:placetype_name": "Airport", "woe:lang": "ENG", "iso:country": "ZM", "meta:provider": ["geoplanet:7.3.1", "geoplanet:7.3.2", "geoplanet:7.4.0", "geoplanet:7.4.1", "geoplanet:7.5.1", "geoplanet:7.5.2", "geoplanet:7.6.0", "geoplanet:7.8.1", "geoplanet:7.9.0", "geoplanet:7.10.0", "geoplanet:8.0.0", "woeplanet:8.0.0"], "meta:indexed": "2020-08-20T20:27:00.010839", "woe:alias_ENG_V": ["MFU Airport", "MFU"], "meta:updated": "2020-10-14T12:08:15.329243", "woe:hierarchy": {"continent": 24865670, "country": 23425003, "town": 0, "planet": 1, "county": 0, "suburb": 0, "state": 2347806, "region": 0, "localadmin": 0}, "woe:timezone_id": 28350714, "woe:hash": "ktwswdnhsky0", "woe:centroid": [31.9347, -13.2597], "geom:latitude": -13.2597, "geom:longitude": 31.9347, "geom:hash": "ktwswdnhsky0", "woe:latitude": -13.2597, "geom:centroid": [31.9347, -13.2597], "woe:longitude": 31.9347, "woe:repo": "woeplanet-airport-zm", "geom:area": 0.0, "woe:scale": 19}}